deptree/__init__.py
deptree/__main__.py
deptree/_i18n.py
deptree/_meta.py
deptree/_pkg_resources.py
deptree/cli.py
deptree-0.0.12.dist-info/LICENSE.txt
deptree-0.0.12.dist-info/METADATA
deptree-0.0.12.dist-info/WHEEL
deptree-0.0.12.dist-info/entry_points.txt
deptree-0.0.12.dist-info/top_level.txt
deptree-0.0.12.dist-info/RECORD
