Metadata-Version: 2.1
Name: deptree
Version: 0.0.12
Summary: Display installed Python projects as a tree of dependencies
Home-page: https://pypi.org/project/deptree/
Author-email: sinoroc <sinoroc.code+python@gmail.com>
License: Apache-2.0
Project-URL: PyPI, https://pypi.org/project/deptree/
Project-URL: GitLab, https://gitlab.com/sinoroc/deptree
Project-URL: GitHub, https://github.com/sinoroc/deptree
License-File: LICENSE.txt
Requires-Dist: importlib-metadata
Requires-Dist: setuptools
Provides-Extra: dev-package
Requires-Dist: build ; extra == 'dev-package'
Requires-Dist: twine ; extra == 'dev-package'
Requires-Dist: zapp ; extra == 'dev-package'
Provides-Extra: dev-test
Requires-Dist: pytest ; extra == 'dev-test'
Requires-Dist: pytest-pycodestyle ; extra == 'dev-test'
Requires-Dist: pytest-pydocstyle ; extra == 'dev-test'
Requires-Dist: pytest-pylint ; extra == 'dev-test'
Requires-Dist: pytest-yapf3 ; extra == 'dev-test'
Requires-Dist: yapf ; extra == 'dev-test'
